risnaberti/nanumber/__init__.py
risnaberti/nanumber/core.py
risnaberti/nanumber/exceptions.py
risnaberti/nanumber/storage/__init__.py
risnaberti/nanumber/storage/base.py
risnaberti/nanumber/storage/memory.py
risnaberti/nanumber/storage/sqlalchemy_storage.py
risnaberti_nanumber-0.2.0.dist-info/licenses/LICENSE
risnaberti_nanumber-0.2.0.dist-info/METADATA
risnaberti_nanumber-0.2.0.dist-info/WHEEL
risnaberti_nanumber-0.2.0.dist-info/top_level.txt
risnaberti_nanumber-0.2.0.dist-info/RECORD
