Metadata-Version: 2.4
Name: risnaberti-nanumber
Version: 0.2.0
Summary: Universal auto-number generator library with flexible templates and multi-database support
Author-email: Risna Berti <risnaberti07@gmail.com>
License: MIT
Project-URL: Homepage, https://github.com/risnaberti/nanumber
Project-URL: Documentation, https://github.com/risnaberti/nanumber#readme
Project-URL: Repository, https://github.com/risnaberti/nanumber
Project-URL: Issues, https://github.com/risnaberti/nanumber/issues
Keywords: autonumber,generator,sqlalchemy,fastapi,django,auto-increment,sequence-generator
Classifier: Development Status :: 4 - Beta
Classifier: Intended Audience :: Developers
Classifier: License :: OSI Approved :: MIT License
Classifier: Programming Language :: Python :: 3
Classifier: Programming Language :: Python :: 3.7
Classifier: Programming Language :: Python :: 3.8
Classifier: Programming Language :: Python :: 3.9
Classifier: Programming Language :: Python :: 3.10
Classifier: Programming Language :: Python :: 3.11
Classifier: Programming Language :: Python :: 3.12
Requires-Python: >=3.7
License-File: LICENSE
Requires-Dist: SQLAlchemy<3.0,>=1.4
Provides-Extra: dev
Requires-Dist: pytest>=7.0; extra == "dev"
Requires-Dist: pytest-cov>=4.0; extra == "dev"
Requires-Dist: black>=23.0; extra == "dev"
Requires-Dist: mypy>=1.0; extra == "dev"
Dynamic: license-file
